pytest_houdini/__init__.py
pytest_houdini/exceptions.py
pytest_houdini/plugin.py
pytest_houdini/tools.py
pytest_houdini/fixtures/__init__.py
pytest_houdini/fixtures/exceptions.py
pytest_houdini/fixtures/hip_file.py
pytest_houdini/fixtures/nodes.py
pytest_houdini/fixtures/other.py
pytest_houdini/fixtures/shelf_tools.py
pytest_houdini/fixtures/soho.py
pytest_houdini/fixtures/ui.py
pytest_houdini-1.1.0.dist-info/LICENSE
pytest_houdini-1.1.0.dist-info/METADATA
pytest_houdini-1.1.0.dist-info/WHEEL
pytest_houdini-1.1.0.dist-info/entry_points.txt
pytest_houdini-1.1.0.dist-info/top_level.txt
pytest_houdini-1.1.0.dist-info/RECORD
