Metadata-Version: 2.1
Name: pytest-houdini
Version: 1.1.0
Summary: pytest plugin for testing code in Houdini.
Home-page: https://github.com/captainhammy/pytest-houdini
Author: Graham Thompson
Author-email: captainhammy@gmail.com
License: MIT
Project-URL: Documentation, https://pytest-houdini.readthedocs.io/
Classifier: Framework :: Pytest
Classifier: License :: OSI Approved :: MIT License
Classifier: Programming Language :: Python
Classifier: Programming Language :: Python :: 3 :: Only
Classifier: Programming Language :: Python :: 3.9
Classifier: Programming Language :: Python :: 3.10
Classifier: Programming Language :: Python :: 3.11
Classifier: Programming Language :: Python :: 3.12
Classifier: Topic :: Software Development :: Testing
Requires-Python: >=3.9.0
License-File: LICENSE
Requires-Dist: pytest
Requires-Dist: pytest-datadir
Requires-Dist: pytest-mock
Provides-Extra: test
Requires-Dist: pytest-cov ; extra == 'test'
Requires-Dist: tox ; extra == 'test'
